README.md
setup.cfg
setup.py
shirtctl/__init__.py
shirtctl.egg-info/PKG-INFO
shirtctl.egg-info/SOURCES.txt
shirtctl.egg-info/dependency_links.txt
shirtctl.egg-info/top_level.txt