Metadata-Version: 2.1
Name: shirtctl
Version: 0.0.2
Summary: The shirtctl Python SDK
Home-page: https://github.com/shirtctl/shirtctl-sdk-python
Author: Blair Hudson
Author-email: blair@shirtctl.com
License: MIT
Keywords: shirtctl,Python,SDK
Platform: UNKNOWN
